gbd.py
gbd_core/__init__.py
gbd_core/api.py
gbd_core/config.py
gbd_core/contexts.py
gbd_core/database.py
gbd_core/grammar.py
gbd_core/query.py
gbd_core/schema.py
gbd_core/util.py
gbd_core/util_argparse.py
gbd_init/__init__.py
gbd_init/feature_extractors.py
gbd_init/gbdhash.py
gbd_init/initializer.py
gbd_init/instance_transformers.py
gbd_server/__init__.py
gbd_server/server.py
gbd_server/static/main.css
gbd_server/static/w3.js
gbd_server/static/img/gbd_logo.jpg
gbd_server/static/img/gbd_logo.png
gbd_server/static/img/gbd_logo_small.png
gbd_server/templates/index.html
gbd_tools-5.0.1.dist-info/licenses/LICENSE
gbd_tools-5.0.1.dist-info/METADATA
gbd_tools-5.0.1.dist-info/WHEEL
gbd_tools-5.0.1.dist-info/entry_points.txt
gbd_tools-5.0.1.dist-info/top_level.txt
gbd_tools-5.0.1.dist-info/RECORD
