Metadata-Version: 2.4
Name: gbd_tools
Version: 5.0.1
Summary: GBD Tools: Maintenance and Distribution of Benchmark Instances and their Attributes
Author-email: Ashlin Iser <iser@kit.edu>
Project-URL: Homepage, https://github.com/Udopia/gbd
Classifier: Programming Language :: Python :: 3
Requires-Python: >=3.6
License-File: LICENSE
Requires-Dist: flask
Requires-Dist: tatsu
Requires-Dist: polars
Requires-Dist: waitress
Requires-Dist: pebble
Requires-Dist: gbdc
Dynamic: license-file
